kozmoml_huggingface/__init__.py
kozmoml_huggingface/codecs/__init__.py
kozmoml_huggingface/codecs/base.py
kozmoml_huggingface/codecs/conversation.py
kozmoml_huggingface/codecs/image.py
kozmoml_huggingface/codecs/json.py
kozmoml_huggingface/codecs/jsonlist.py
kozmoml_huggingface/codecs/numpylist.py
kozmoml_huggingface/codecs/raw.py
kozmoml_huggingface/codecs/utils.py
kozmoml_huggingface/common.py
kozmoml_huggingface/errors.py
kozmoml_huggingface/metadata.py
kozmoml_huggingface/runtime.py
kozmoml_huggingface/settings.py
kozmoml_huggingface/version.py
kozmoml_huggingface-0.1.0.dev1.dist-info/LICENSE
kozmoml_huggingface-0.1.0.dev1.dist-info/METADATA
kozmoml_huggingface-0.1.0.dev1.dist-info/WHEEL
kozmoml_huggingface-0.1.0.dev1.dist-info/RECORD
