Metadata-Version: 2.1
Name: kozmoml-huggingface
Version: 0.1.0.dev1
Summary: HuggingFace runtime for KozmoML
License: Apache-2.0
Author: KozmoAI
Author-email: developers@kozmoai.io
Requires-Python: >=3.9,<3.12
Classifier: License :: OSI Approved :: Apache Software License
Classifier: Programming Language :: Python :: 3
Classifier: Programming Language :: Python :: 3.9
Classifier: Programming Language :: Python :: 3.10
Classifier: Programming Language :: Python :: 3.11
Requires-Dist: kozmoml
Requires-Dist: optimum[onnxruntime] (>=1.4,<2.0)
Requires-Dist: pillow
Requires-Dist: pydantic (<2.0.0)
Requires-Dist: tensorflow
